bdcctools/__init__.py
bdcctools/io.py
bdcctools/utils.py
bdcctools/verification.py
bdcctools/cli/__init__.py
bdcctools/cli/cli.py
bdcctools/cli/commands/__init__.py
bdcctools/cli/commands/download.py
bdcctools/cli/commands/geographic.py
bdcctools/cli/commands/setup.py
bdcctools/cli/commands/taxonomic.py
bdcctools/cli/config/logger.ini
bdcctools/cli/config/settings.ini
bdcctools/cli/options/__init__.py
bdcctools/cli/options/geographic.py
bdcctools/cli/options/taxonomic.py
bdcctools/cli/util/__init__.py
bdcctools/cli/util/config.py
bdcctools/cli/util/logger.py
bdcctools/geographic/__init__.py
bdcctools/geographic/local.py
bdcctools/geographic/utils.py
bdcctools/taxonomic/__init__.py
bdcctools/taxonomic/local.py
bdcctools/taxonomic/parsing.py
bdcctools/taxonomic/utils.py
bdcctools/taxonomic/constants/__init__.py
bdcctools/taxonomic/constants/qualifiers.py
bdcctools/taxonomic/web/__init__.py
bdcctools/taxonomic/web/gnr.py
bdcctools/taxonomic/web/iucn.py
bdcctools/taxonomic/web/speciesplus.py
bdcctools-0.3.1.dist-info/LICENSE.txt
bdcctools-0.3.1.dist-info/METADATA
bdcctools-0.3.1.dist-info/WHEEL
bdcctools-0.3.1.dist-info/entry_points.txt
bdcctools-0.3.1.dist-info/top_level.txt
bdcctools-0.3.1.dist-info/RECORD
