Metadata-Version: 2.1
Name: bdcctools
Version: 0.3.1
Summary: Biodiversity Data Cleaning and Curation Tools
Home-page: https://github.com/PEM-Humboldt/bdcc-tools
Author: Marcelo Villa-Piñeros
Author-email: mvilla@humboldt.org.co
License: UNKNOWN
Platform: UNKNOWN
Classifier: Programming Language :: Python :: 3
Classifier: License :: OSI Approved :: MIT License
Classifier: Operating System :: OS Independent
License-File: LICENSE.txt
Requires-Dist: appdirs
Requires-Dist: click
Requires-Dist: Fiona
Requires-Dist: gdal
Requires-Dist: gdown
Requires-Dist: geopandas
Requires-Dist: numpy
Requires-Dist: openpyxl
Requires-Dist: pandas
Requires-Dist: pygeos
Requires-Dist: rapidfuzz
Requires-Dist: rasterio
Requires-Dist: rasterstats
Requires-Dist: requests
Requires-Dist: Rtree
Requires-Dist: scipy
Requires-Dist: shapely
Provides-Extra: dev
Requires-Dist: black ; extra == 'dev'
Requires-Dist: ipython ; extra == 'dev'
Provides-Extra: test
Requires-Dist: pytest ; extra == 'test'
